<?xml version="1.0" encoding="UTF-8"?>
<export version="E">
  <design>
    <source>C:\gh\oomlout_oomp_project_bot_v_2\projects\adafruit_adafruit_eyespi_bff_pcb_adafruit_eyespi_bff_pcb\current_version\working\working.kicad_sch</source>
    <date>11/09/2023 19:00:33</date>
    <tool>Eeschema 7.0.6</tool>
    <sheet number="1" name="/" tstamps="/">
      <title_block>
        <title/>
        <company/>
        <rev/>
        <date/>
        <source>working.kicad_sch</source>
        <comment number="1" value=""/>
        <comment number="2" value=""/>
        <comment number="3" value=""/>
        <comment number="4" value=""/>
        <comment number="5" value=""/>
        <comment number="6" value=""/>
        <comment number="7" value=""/>
        <comment number="8" value=""/>
        <comment number="9" value=""/>
      </title_block>
    </sheet>
  </design>
  <components>
    <comp ref="JP1">
      <value>HEADER-1X7_CASTEL</value>
      <footprint>working:1X07_CASTEL</footprint>
      <libsource lib="working-eagle-import" part="HEADER-1X7_CASTEL" description=""/>
      <property name="Sheetname" value=""/>
      <property name="Sheetfile" value="working.kicad_sch"/>
      <sheetpath names="/" tstamps="/"/>
      <tstamps>e4d774ef-fd3e-4974-aee2-275bb3f9f0ac</tstamps>
    </comp>
    <comp ref="JP2">
      <value>HEADER-1X12MM</value>
      <footprint>working:1X01_2MM</footprint>
      <libsource lib="working-eagle-import" part="HEADER-1X12MM" description=""/>
      <property name="Sheetname" value=""/>
      <property name="Sheetfile" value="working.kicad_sch"/>
      <sheetpath names="/" tstamps="/"/>
      <tstamps>0c6c27b7-4cca-4587-8ed3-2f6d8b1ba11a</tstamps>
    </comp>
    <comp ref="JP3">
      <value>HEADER-1X7_CASTEL</value>
      <footprint>working:1X07_CASTEL</footprint>
      <libsource lib="working-eagle-import" part="HEADER-1X7_CASTEL" description=""/>
      <property name="Sheetname" value=""/>
      <property name="Sheetfile" value="working.kicad_sch"/>
      <sheetpath names="/" tstamps="/"/>
      <tstamps>ba58ff42-65ce-4658-94f5-735d9e724af9</tstamps>
    </comp>
    <comp ref="JP4">
      <value>HEADER-1X12MM</value>
      <footprint>working:1X01_2MM</footprint>
      <libsource lib="working-eagle-import" part="HEADER-1X12MM" description=""/>
      <property name="Sheetname" value=""/>
      <property name="Sheetfile" value="working.kicad_sch"/>
      <sheetpath names="/" tstamps="/"/>
      <tstamps>6b5c1a27-8fb2-4077-bceb-1cd6e074b4d5</tstamps>
    </comp>
    <comp ref="JP5">
      <value>HEADER-1X12MM</value>
      <footprint>working:1X01_2MM</footprint>
      <libsource lib="working-eagle-import" part="HEADER-1X12MM" description=""/>
      <property name="Sheetname" value=""/>
      <property name="Sheetfile" value="working.kicad_sch"/>
      <sheetpath names="/" tstamps="/"/>
      <tstamps>9f5b9765-ef39-4939-b1f5-ab4a0f6545bc</tstamps>
    </comp>
    <comp ref="JP6">
      <value>HEADER-1X12MM</value>
      <footprint>working:1X01_2MM</footprint>
      <libsource lib="working-eagle-import" part="HEADER-1X12MM" description=""/>
      <property name="Sheetname" value=""/>
      <property name="Sheetfile" value="working.kicad_sch"/>
      <sheetpath names="/" tstamps="/"/>
      <tstamps>2e6fdbd9-954e-453f-bce6-b6c89453c894</tstamps>
    </comp>
    <comp ref="JP7">
      <value>HEADER-1X12MM</value>
      <footprint>working:1X01_2MM</footprint>
      <libsource lib="working-eagle-import" part="HEADER-1X12MM" description=""/>
      <property name="Sheetname" value=""/>
      <property name="Sheetfile" value="working.kicad_sch"/>
      <sheetpath names="/" tstamps="/"/>
      <tstamps>412eb06d-028d-445b-85df-b86f5f16819a</tstamps>
    </comp>
    <comp ref="JP8">
      <value>HEADER-1X12MM</value>
      <footprint>working:1X01_2MM</footprint>
      <libsource lib="working-eagle-import" part="HEADER-1X12MM" description=""/>
      <property name="Sheetname" value=""/>
      <property name="Sheetfile" value="working.kicad_sch"/>
      <sheetpath names="/" tstamps="/"/>
      <tstamps>4b55fc24-4d65-460c-b24d-5ece5d111dc6</tstamps>
    </comp>
    <comp ref="JP9">
      <value>HEADER-1X12MM</value>
      <footprint>working:1X01_2MM</footprint>
      <libsource lib="working-eagle-import" part="HEADER-1X12MM" description=""/>
      <property name="Sheetname" value=""/>
      <property name="Sheetfile" value="working.kicad_sch"/>
      <sheetpath names="/" tstamps="/"/>
      <tstamps>5e600692-4379-4ec8-abfa-c6bf284d3dd2</tstamps>
    </comp>
    <comp ref="JP10">
      <value>HEADER-1X12MM</value>
      <footprint>working:1X01_2MM</footprint>
      <libsource lib="working-eagle-import" part="HEADER-1X12MM" description=""/>
      <property name="Sheetname" value=""/>
      <property name="Sheetfile" value="working.kicad_sch"/>
      <sheetpath names="/" tstamps="/"/>
      <tstamps>a97284c1-efbb-4a9b-9acb-2836ca4985d9</tstamps>
    </comp>
    <comp ref="SJ1">
      <value>SOLDERJUMPER_CLOSED</value>
      <footprint>working:SOLDERJUMPER_CLOSEDWIRE</footprint>
      <libsource lib="working-eagle-import" part="SOLDERJUMPER_CLOSED" description=""/>
      <property name="Sheetname" value=""/>
      <property name="Sheetfile" value="working.kicad_sch"/>
      <sheetpath names="/" tstamps="/"/>
      <tstamps>dc5fb3cb-4cd7-43cb-ada5-876573586afb</tstamps>
    </comp>
    <comp ref="SJ2">
      <value>SOLDERJUMPER_CLOSED</value>
      <footprint>working:SOLDERJUMPER_CLOSEDWIRE</footprint>
      <libsource lib="working-eagle-import" part="SOLDERJUMPER_CLOSED" description=""/>
      <property name="Sheetname" value=""/>
      <property name="Sheetfile" value="working.kicad_sch"/>
      <sheetpath names="/" tstamps="/"/>
      <tstamps>9c18305f-dff1-46f9-bf7e-e7d15c32734f</tstamps>
    </comp>
    <comp ref="SJ3">
      <value>SOLDERJUMPER_CLOSED</value>
      <footprint>working:SOLDERJUMPER_CLOSEDWIRE</footprint>
      <libsource lib="working-eagle-import" part="SOLDERJUMPER_CLOSED" description=""/>
      <property name="Sheetname" value=""/>
      <property name="Sheetfile" value="working.kicad_sch"/>
      <sheetpath names="/" tstamps="/"/>
      <tstamps>9dd97694-de9f-44ac-bc06-02d96b1fb374</tstamps>
    </comp>
    <comp ref="SJ4">
      <value>SOLDERJUMPER_CLOSED</value>
      <footprint>working:SOLDERJUMPER_CLOSEDWIRE</footprint>
      <libsource lib="working-eagle-import" part="SOLDERJUMPER_CLOSED" description=""/>
      <property name="Sheetname" value=""/>
      <property name="Sheetfile" value="working.kicad_sch"/>
      <sheetpath names="/" tstamps="/"/>
      <tstamps>714bed31-f2c3-4d14-a440-497ece2114c9</tstamps>
    </comp>
    <comp ref="SJ5">
      <value>SOLDERJUMPER_CLOSED</value>
      <footprint>working:SOLDERJUMPER_CLOSEDWIRE</footprint>
      <libsource lib="working-eagle-import" part="SOLDERJUMPER_CLOSED" description=""/>
      <property name="Sheetname" value=""/>
      <property name="Sheetfile" value="working.kicad_sch"/>
      <sheetpath names="/" tstamps="/"/>
      <tstamps>654845dd-2a82-496c-b5b3-e0b306a269f3</tstamps>
    </comp>
    <comp ref="SJ6">
      <value>SOLDERJUMPER_CLOSED</value>
      <footprint>working:SOLDERJUMPER_CLOSEDWIRE</footprint>
      <libsource lib="working-eagle-import" part="SOLDERJUMPER_CLOSED" description=""/>
      <property name="Sheetname" value=""/>
      <property name="Sheetfile" value="working.kicad_sch"/>
      <sheetpath names="/" tstamps="/"/>
      <tstamps>9d11bcff-1559-493d-810f-9aba8940c310</tstamps>
    </comp>
    <comp ref="U$6">
      <value>FIDUCIAL_1MM</value>
      <footprint>working:FIDUCIAL_1MM</footprint>
      <libsource lib="working-eagle-import" part="FIDUCIAL_1MM" description=""/>
      <property name="Sheetname" value=""/>
      <property name="Sheetfile" value="working.kicad_sch"/>
      <sheetpath names="/" tstamps="/"/>
      <tstamps>caa46eaa-ecc3-4835-a0f2-101c80c35c41</tstamps>
    </comp>
    <comp ref="U$8">
      <value>FIDUCIAL_1MM</value>
      <footprint>working:FIDUCIAL_1MM</footprint>
      <libsource lib="working-eagle-import" part="FIDUCIAL_1MM" description=""/>
      <property name="Sheetname" value=""/>
      <property name="Sheetfile" value="working.kicad_sch"/>
      <sheetpath names="/" tstamps="/"/>
      <tstamps>35fb6d8d-4532-4321-a73f-a038fe77fa5b</tstamps>
    </comp>
    <comp ref="X1">
      <value>EYE_SPI_DISPLAY_SLIM</value>
      <footprint>working:EYE_SPI_DISPLAY_SLIM</footprint>
      <libsource lib="working-eagle-import" part="EYE_SPI_DISPLAY_SLIM" description=""/>
      <property name="Sheetname" value=""/>
      <property name="Sheetfile" value="working.kicad_sch"/>
      <sheetpath names="/" tstamps="/"/>
      <tstamps>adbe0d0c-7cfc-42a5-8f95-76c06dc93e3a</tstamps>
    </comp>
  </components>
  <libparts>
    <libpart lib="working-eagle-import" part="EYE_SPI_DISPLAY_SLIM">
      <fields>
        <field name="Reference">X</field>
        <field name="Footprint">working:EYE_SPI_DISPLAY_SLIM</field>
      </fields>
      <pins>
        <pin num="1" name="VCC" type="power_in"/>
        <pin num="2" name="BACKLITE" type="input"/>
        <pin num="3" name="GND" type="power_in"/>
        <pin num="4" name="SCK" type="input"/>
        <pin num="5" name="MOSI" type="input"/>
        <pin num="6" name="MISO" type="output"/>
        <pin num="7" name="DC" type="input"/>
        <pin num="8" name="RESET" type="input"/>
        <pin num="9" name="DISP_CS" type="input"/>
        <pin num="10" name="SD_CS" type="input"/>
        <pin num="11" name="MEM_CS" type="input"/>
        <pin num="12" name="TS_CS" type="input"/>
        <pin num="13" name="SCL" type="input"/>
        <pin num="14" name="SDA" type="bidirectional"/>
        <pin num="15" name="INT" type="output"/>
        <pin num="16" name="BUSY/TE" type="output"/>
        <pin num="17" name="GPIO1" type="passive"/>
        <pin num="18" name="GPIO2" type="passive"/>
        <pin num="SUPPORT1" name="GND" type="power_in"/>
        <pin num="SUPPORT2" name="GND" type="power_in"/>
      </pins>
    </libpart>
    <libpart lib="working-eagle-import" part="FIDUCIAL_1MM">
      <fields>
        <field name="Reference">FID</field>
        <field name="Footprint">working:FIDUCIAL_1MM</field>
      </fields>
    </libpart>
    <libpart lib="working-eagle-import" part="HEADER-1X12MM">
      <fields>
        <field name="Reference">JP</field>
        <field name="Footprint">working:1X01_2MM</field>
      </fields>
      <pins>
        <pin num="1" name="1" type="passive"/>
      </pins>
    </libpart>
    <libpart lib="working-eagle-import" part="HEADER-1X7_CASTEL">
      <fields>
        <field name="Reference">JP</field>
        <field name="Footprint">working:1X07_CASTEL</field>
      </fields>
      <pins>
        <pin num="1" name="1" type="passive"/>
        <pin num="1C" name="1" type="passive"/>
        <pin num="2" name="2" type="passive"/>
        <pin num="2C" name="2" type="passive"/>
        <pin num="3" name="3" type="passive"/>
        <pin num="3C" name="3" type="passive"/>
        <pin num="4" name="4" type="passive"/>
        <pin num="4C" name="4" type="passive"/>
        <pin num="5" name="5" type="passive"/>
        <pin num="5C" name="5" type="passive"/>
        <pin num="6" name="6" type="passive"/>
        <pin num="6C" name="6" type="passive"/>
        <pin num="7" name="7" type="passive"/>
        <pin num="7C" name="7" type="passive"/>
      </pins>
    </libpart>
    <libpart lib="working-eagle-import" part="SOLDERJUMPER_CLOSED">
      <fields>
        <field name="Reference">SJ</field>
        <field name="Footprint">working:SOLDERJUMPER_CLOSEDWIRE</field>
      </fields>
      <pins>
        <pin num="1" name="1" type="passive"/>
        <pin num="2" name="2" type="passive"/>
      </pins>
    </libpart>
  </libparts>
  <libraries/>
  <nets>
    <net code="1" name="+5V">
      <node ref="JP3" pin="7" pinfunction="7" pintype="passive"/>
      <node ref="JP3" pin="7C" pinfunction="7" pintype="passive"/>
    </net>
    <net code="2" name="/A0">
      <node ref="JP1" pin="1" pinfunction="1" pintype="passive"/>
      <node ref="JP1" pin="1C" pinfunction="1" pintype="passive"/>
      <node ref="SJ6" pin="1" pinfunction="1" pintype="passive"/>
    </net>
    <net code="3" name="/A1">
      <node ref="JP1" pin="2" pinfunction="2" pintype="passive"/>
      <node ref="JP1" pin="2C" pinfunction="2" pintype="passive"/>
      <node ref="SJ5" pin="1" pinfunction="1" pintype="passive"/>
    </net>
    <net code="4" name="/A2">
      <node ref="JP1" pin="3" pinfunction="3" pintype="passive"/>
      <node ref="JP1" pin="3C" pinfunction="3" pintype="passive"/>
      <node ref="SJ4" pin="1" pinfunction="1" pintype="passive"/>
    </net>
    <net code="5" name="/A3">
      <node ref="JP1" pin="4" pinfunction="4" pintype="passive"/>
      <node ref="JP1" pin="4C" pinfunction="4" pintype="passive"/>
      <node ref="SJ3" pin="1" pinfunction="1" pintype="passive"/>
    </net>
    <net code="6" name="/INT">
      <node ref="JP2" pin="1" pinfunction="1" pintype="passive"/>
      <node ref="SJ6" pin="2" pinfunction="2" pintype="passive"/>
      <node ref="X1" pin="15" pinfunction="INT" pintype="output"/>
    </net>
    <net code="7" name="/LITE">
      <node ref="JP9" pin="1" pinfunction="1" pintype="passive"/>
      <node ref="X1" pin="2" pinfunction="BACKLITE" pintype="input"/>
    </net>
    <net code="8" name="/MEM_CS">
      <node ref="JP5" pin="1" pinfunction="1" pintype="passive"/>
      <node ref="SJ4" pin="2" pinfunction="2" pintype="passive"/>
      <node ref="X1" pin="11" pinfunction="MEM_CS" pintype="input"/>
    </net>
    <net code="9" name="/MISO">
      <node ref="JP3" pin="3" pinfunction="3" pintype="passive"/>
      <node ref="JP3" pin="3C" pinfunction="3" pintype="passive"/>
      <node ref="X1" pin="6" pinfunction="MISO" pintype="output"/>
    </net>
    <net code="10" name="/MOSI">
      <node ref="JP3" pin="4" pinfunction="4" pintype="passive"/>
      <node ref="JP3" pin="4C" pinfunction="4" pintype="passive"/>
      <node ref="X1" pin="5" pinfunction="MOSI" pintype="input"/>
    </net>
    <net code="11" name="/RX">
      <node ref="JP3" pin="1" pinfunction="1" pintype="passive"/>
      <node ref="JP3" pin="1C" pinfunction="1" pintype="passive"/>
      <node ref="SJ1" pin="1" pinfunction="1" pintype="passive"/>
    </net>
    <net code="12" name="/SCK">
      <node ref="JP3" pin="2" pinfunction="2" pintype="passive"/>
      <node ref="JP3" pin="2C" pinfunction="2" pintype="passive"/>
      <node ref="X1" pin="4" pinfunction="SCK" pintype="input"/>
    </net>
    <net code="13" name="/SCL">
      <node ref="JP1" pin="6" pinfunction="6" pintype="passive"/>
      <node ref="JP1" pin="6C" pinfunction="6" pintype="passive"/>
      <node ref="X1" pin="13" pinfunction="SCL" pintype="input"/>
    </net>
    <net code="14" name="/SDA">
      <node ref="JP1" pin="5" pinfunction="5" pintype="passive"/>
      <node ref="JP1" pin="5C" pinfunction="5" pintype="passive"/>
      <node ref="X1" pin="14" pinfunction="SDA" pintype="bidirectional"/>
    </net>
    <net code="15" name="/SD_CS">
      <node ref="JP6" pin="1" pinfunction="1" pintype="passive"/>
      <node ref="SJ3" pin="2" pinfunction="2" pintype="passive"/>
      <node ref="X1" pin="10" pinfunction="SD_CS" pintype="input"/>
    </net>
    <net code="16" name="/TFT_CS">
      <node ref="JP7" pin="1" pinfunction="1" pintype="passive"/>
      <node ref="SJ2" pin="2" pinfunction="2" pintype="passive"/>
      <node ref="X1" pin="9" pinfunction="DISP_CS" pintype="input"/>
    </net>
    <net code="17" name="/TFT_DC">
      <node ref="JP8" pin="1" pinfunction="1" pintype="passive"/>
      <node ref="SJ1" pin="2" pinfunction="2" pintype="passive"/>
      <node ref="X1" pin="7" pinfunction="DC" pintype="input"/>
    </net>
    <net code="18" name="/TS_CS">
      <node ref="JP4" pin="1" pinfunction="1" pintype="passive"/>
      <node ref="SJ5" pin="2" pinfunction="2" pintype="passive"/>
      <node ref="X1" pin="12" pinfunction="TS_CS" pintype="input"/>
    </net>
    <net code="19" name="/TX">
      <node ref="JP1" pin="7" pinfunction="7" pintype="passive"/>
      <node ref="JP1" pin="7C" pinfunction="7" pintype="passive"/>
      <node ref="SJ2" pin="1" pinfunction="1" pintype="passive"/>
    </net>
    <net code="20" name="/~{RESET}">
      <node ref="JP10" pin="1" pinfunction="1" pintype="passive"/>
      <node ref="X1" pin="8" pinfunction="RESET" pintype="input"/>
    </net>
    <net code="21" name="3.3V">
      <node ref="JP3" pin="5" pinfunction="5" pintype="passive"/>
      <node ref="JP3" pin="5C" pinfunction="5" pintype="passive"/>
      <node ref="X1" pin="1" pinfunction="VCC" pintype="power_in"/>
    </net>
    <net code="22" name="GND">
      <node ref="JP3" pin="6" pinfunction="6" pintype="passive"/>
      <node ref="JP3" pin="6C" pinfunction="6" pintype="passive"/>
      <node ref="X1" pin="3" pinfunction="GND" pintype="power_in"/>
      <node ref="X1" pin="SUPPORT1" pinfunction="GND" pintype="power_in"/>
      <node ref="X1" pin="SUPPORT2" pinfunction="GND" pintype="power_in"/>
    </net>
    <net code="23" name="unconnected-(X1-BUSY{slash}TE-Pad16)">
      <node ref="X1" pin="16" pinfunction="BUSY/TE" pintype="output"/>
    </net>
    <net code="24" name="unconnected-(X1-GPIO1-Pad17)">
      <node ref="X1" pin="17" pinfunction="GPIO1" pintype="passive"/>
    </net>
    <net code="25" name="unconnected-(X1-GPIO2-Pad18)">
      <node ref="X1" pin="18" pinfunction="GPIO2" pintype="passive"/>
    </net>
  </nets>
</export>
