<?xml version="1.0" encoding="UTF-8"?>
<export version="E">
  <design>
    <source>C:\gh\oomlout_oomp_project_bot_v_2\projects\adafruit_adafruit_vcnl4040_pcb_adafruit_vcnl4040\current_version\working\_autosave-working.kicad_sch</source>
    <date>22/09/2023 14:50:10</date>
    <tool>Eeschema 7.0.6</tool>
    <sheet number="1" name="/" tstamps="/">
      <title_block>
        <title/>
        <company/>
        <rev/>
        <date/>
        <source>_autosave-working.kicad_sch</source>
        <comment number="1" value=""/>
        <comment number="2" value=""/>
        <comment number="3" value=""/>
        <comment number="4" value=""/>
        <comment number="5" value=""/>
        <comment number="6" value=""/>
        <comment number="7" value=""/>
        <comment number="8" value=""/>
        <comment number="9" value=""/>
      </title_block>
    </sheet>
  </design>
  <components>
    <comp ref="C1">
      <value>0.1uF</value>
      <footprint>working:0603-NO</footprint>
      <libsource lib="working-eagle-import" part="CAP_CERAMIC0603_NO" description=""/>
      <property name="Sheetname" value=""/>
      <property name="Sheetfile" value="_autosave-working.kicad_sch"/>
      <sheetpath names="/" tstamps="/"/>
      <tstamps>5e536825-1062-472b-87d5-1dca69f08876</tstamps>
    </comp>
    <comp ref="C2">
      <value>10uF</value>
      <footprint>working:0805-NO</footprint>
      <libsource lib="working-eagle-import" part="CAP_CERAMIC0805-NOOUTLINE" description=""/>
      <property name="Sheetname" value=""/>
      <property name="Sheetfile" value="_autosave-working.kicad_sch"/>
      <sheetpath names="/" tstamps="/"/>
      <tstamps>0c594199-8415-442a-9cc3-44b0e782fdf8</tstamps>
    </comp>
    <comp ref="C3">
      <value>10uF</value>
      <footprint>working:0805-NO</footprint>
      <libsource lib="working-eagle-import" part="CAP_CERAMIC0805-NOOUTLINE" description=""/>
      <property name="Sheetname" value=""/>
      <property name="Sheetfile" value="_autosave-working.kicad_sch"/>
      <sheetpath names="/" tstamps="/"/>
      <tstamps>cd22b197-3749-4fb3-b082-f4a5e92efba9</tstamps>
    </comp>
    <comp ref="CONN3">
      <value>STEMMA_I2C_QT</value>
      <footprint>working:JST_SH4</footprint>
      <libsource lib="working-eagle-import" part="STEMMA_I2C_QT" description=""/>
      <property name="Sheetname" value=""/>
      <property name="Sheetfile" value="_autosave-working.kicad_sch"/>
      <sheetpath names="/" tstamps="/"/>
      <tstamps>3ef40ebd-877a-44e2-9578-435694c79103</tstamps>
    </comp>
    <comp ref="CONN4">
      <value>STEMMA_I2C_QT</value>
      <footprint>working:JST_SH4</footprint>
      <libsource lib="working-eagle-import" part="STEMMA_I2C_QT" description=""/>
      <property name="Sheetname" value=""/>
      <property name="Sheetfile" value="_autosave-working.kicad_sch"/>
      <sheetpath names="/" tstamps="/"/>
      <tstamps>34c19b7d-c44f-4e31-a458-bbc6d8fb271b</tstamps>
    </comp>
    <comp ref="D1">
      <value>GREEN</value>
      <footprint>working:CHIPLED_0603_NOOUTLINE</footprint>
      <libsource lib="working-eagle-import" part="LED0603_NOOUTLINE" description=""/>
      <property name="Sheetname" value=""/>
      <property name="Sheetfile" value="_autosave-working.kicad_sch"/>
      <sheetpath names="/" tstamps="/"/>
      <tstamps>966918d4-8397-4a64-b79b-000b3e35660a</tstamps>
    </comp>
    <comp ref="FID3">
      <value>FIDUCIAL_1MM</value>
      <footprint>working:FIDUCIAL_1MM</footprint>
      <libsource lib="working-eagle-import" part="FIDUCIAL_1MM" description=""/>
      <property name="Sheetname" value=""/>
      <property name="Sheetfile" value="_autosave-working.kicad_sch"/>
      <sheetpath names="/" tstamps="/"/>
      <tstamps>7cd532f5-c18b-447f-b85b-2f1588ee50e0</tstamps>
    </comp>
    <comp ref="FID4">
      <value>FIDUCIAL_1MM</value>
      <footprint>working:FIDUCIAL_1MM</footprint>
      <libsource lib="working-eagle-import" part="FIDUCIAL_1MM" description=""/>
      <property name="Sheetname" value=""/>
      <property name="Sheetfile" value="_autosave-working.kicad_sch"/>
      <sheetpath names="/" tstamps="/"/>
      <tstamps>c3b33e3c-0b43-4ec3-8d31-c15b73038b9f</tstamps>
    </comp>
    <comp ref="JP1">
      <value>HEADER-1X670MIL</value>
      <footprint>working:1X06_ROUND_70</footprint>
      <libsource lib="working-eagle-import" part="HEADER-1X670MIL" description=""/>
      <property name="Sheetname" value=""/>
      <property name="Sheetfile" value="_autosave-working.kicad_sch"/>
      <sheetpath names="/" tstamps="/"/>
      <tstamps>cccd84f6-e00c-4195-b47d-598e5cdb4bd1</tstamps>
    </comp>
    <comp ref="Q2">
      <value>BSS138</value>
      <footprint>working:SOT363</footprint>
      <libsource lib="working-eagle-import" part="MOSFET-N_DUAL" description=""/>
      <property name="Sheetname" value=""/>
      <property name="Sheetfile" value="_autosave-working.kicad_sch"/>
      <sheetpath names="/" tstamps="/"/>
      <tstamps>a878a898-daad-4c46-8ad9-32c81877c5ac a111f8a1-23bb-49b6-be06-36e15bab5dad</tstamps>
    </comp>
    <comp ref="R1">
      <value>10K</value>
      <footprint>working:0603-NO</footprint>
      <libsource lib="working-eagle-import" part="RESISTOR_0603_NOOUT" description=""/>
      <property name="Sheetname" value=""/>
      <property name="Sheetfile" value="_autosave-working.kicad_sch"/>
      <sheetpath names="/" tstamps="/"/>
      <tstamps>05c7354f-54a3-41ce-a1f8-d3d515ab2cbc</tstamps>
    </comp>
    <comp ref="R3">
      <value>10K</value>
      <footprint>working:RESPACK_4X0603</footprint>
      <libsource lib="working-eagle-import" part="RESISTOR_4PACK" description=""/>
      <property name="Sheetname" value=""/>
      <property name="Sheetfile" value="_autosave-working.kicad_sch"/>
      <sheetpath names="/" tstamps="/"/>
      <tstamps>e968bcd9-e6c8-48b2-b029-af74520c6224 e10e1d9c-b3fb-497c-a89c-ffb9157e8fbd 6ebcbaaf-9b6d-4e25-b462-637670ffe4a8 3757cd9b-2faf-464e-aa2d-15300f9207b3</tstamps>
    </comp>
    <comp ref="U$1">
      <value>MOUNTINGHOLE2.5</value>
      <footprint>working:MOUNTINGHOLE_2.5_PLATED</footprint>
      <libsource lib="working-eagle-import" part="MOUNTINGHOLE2.5" description=""/>
      <property name="Sheetname" value=""/>
      <property name="Sheetfile" value="_autosave-working.kicad_sch"/>
      <sheetpath names="/" tstamps="/"/>
      <tstamps>2a85248c-5b0f-4f36-be6b-2fdbafa4ee60</tstamps>
    </comp>
    <comp ref="U$17">
      <value>MOUNTINGHOLE2.5</value>
      <footprint>working:MOUNTINGHOLE_2.5_PLATED</footprint>
      <libsource lib="working-eagle-import" part="MOUNTINGHOLE2.5" description=""/>
      <property name="Sheetname" value=""/>
      <property name="Sheetfile" value="_autosave-working.kicad_sch"/>
      <sheetpath names="/" tstamps="/"/>
      <tstamps>41774376-368e-4ee2-beb4-3e0cfe6b894e</tstamps>
    </comp>
    <comp ref="U$19">
      <value>MOUNTINGHOLE2.5</value>
      <footprint>working:MOUNTINGHOLE_2.5_PLATED</footprint>
      <libsource lib="working-eagle-import" part="MOUNTINGHOLE2.5" description=""/>
      <property name="Sheetname" value=""/>
      <property name="Sheetfile" value="_autosave-working.kicad_sch"/>
      <sheetpath names="/" tstamps="/"/>
      <tstamps>8d120c07-66fb-41af-b6bd-5e0115c6e35a</tstamps>
    </comp>
    <comp ref="U$21">
      <value>MOUNTINGHOLE2.5</value>
      <footprint>working:MOUNTINGHOLE_2.5_PLATED</footprint>
      <libsource lib="working-eagle-import" part="MOUNTINGHOLE2.5" description=""/>
      <property name="Sheetname" value=""/>
      <property name="Sheetfile" value="_autosave-working.kicad_sch"/>
      <sheetpath names="/" tstamps="/"/>
      <tstamps>6833e242-0055-48f9-b656-f87623ac8361</tstamps>
    </comp>
    <comp ref="U2">
      <value>AP2112K-3.3</value>
      <footprint>working:SOT23-5</footprint>
      <libsource lib="working-eagle-import" part="VREG_SOT23-5" description=""/>
      <property name="Sheetname" value=""/>
      <property name="Sheetfile" value="_autosave-working.kicad_sch"/>
      <sheetpath names="/" tstamps="/"/>
      <tstamps>ba8103ec-8257-4ae4-bb8d-a90021d5f6ed</tstamps>
    </comp>
    <comp ref="U3">
      <value>VCNL4040M3OE</value>
      <footprint>working:VISHAY_VCNL4040_4X2X1.1</footprint>
      <libsource lib="working-eagle-import" part="VCNL4040M3OE" description=""/>
      <property name="Sheetname" value=""/>
      <property name="Sheetfile" value="_autosave-working.kicad_sch"/>
      <sheetpath names="/" tstamps="/"/>
      <tstamps>3231b0a8-e0c9-4a57-b2d2-a29e723f14d1</tstamps>
    </comp>
  </components>
  <libparts>
    <libpart lib="working-eagle-import" part="CAP_CERAMIC0603_NO">
      <fields>
        <field name="Reference">C</field>
        <field name="Footprint">working:0603-NO</field>
      </fields>
      <pins>
        <pin num="1" name="1" type="passive"/>
        <pin num="2" name="2" type="passive"/>
      </pins>
    </libpart>
    <libpart lib="working-eagle-import" part="CAP_CERAMIC0805-NOOUTLINE">
      <fields>
        <field name="Reference">C</field>
        <field name="Footprint">working:0805-NO</field>
      </fields>
      <pins>
        <pin num="1" name="1" type="passive"/>
        <pin num="2" name="2" type="passive"/>
      </pins>
    </libpart>
    <libpart lib="working-eagle-import" part="FIDUCIAL_1MM">
      <fields>
        <field name="Reference">FID</field>
        <field name="Footprint">working:FIDUCIAL_1MM</field>
      </fields>
    </libpart>
    <libpart lib="working-eagle-import" part="HEADER-1X670MIL">
      <fields>
        <field name="Reference">JP</field>
        <field name="Footprint">working:1X06_ROUND_70</field>
      </fields>
      <pins>
        <pin num="1" name="1" type="passive"/>
        <pin num="2" name="2" type="passive"/>
        <pin num="3" name="3" type="passive"/>
        <pin num="4" name="4" type="passive"/>
        <pin num="5" name="5" type="passive"/>
        <pin num="6" name="6" type="passive"/>
      </pins>
    </libpart>
    <libpart lib="working-eagle-import" part="LED0603_NOOUTLINE">
      <fields>
        <field name="Reference">D</field>
        <field name="Footprint">working:CHIPLED_0603_NOOUTLINE</field>
      </fields>
      <pins>
        <pin num="A" name="A" type="passive"/>
        <pin num="C" name="C" type="passive"/>
      </pins>
    </libpart>
    <libpart lib="working-eagle-import" part="MOSFET-N_DUAL">
      <fields>
        <field name="Reference">Q</field>
        <field name="Footprint">working:SOT363</field>
      </fields>
      <pins>
        <pin num="1" name="S" type="bidirectional"/>
        <pin num="2" name="G" type="bidirectional"/>
        <pin num="3" name="D" type="bidirectional"/>
        <pin num="4" name="S" type="bidirectional"/>
        <pin num="5" name="G" type="bidirectional"/>
        <pin num="6" name="D" type="bidirectional"/>
      </pins>
    </libpart>
    <libpart lib="working-eagle-import" part="MOUNTINGHOLE2.5">
      <fields>
        <field name="Footprint">working:MOUNTINGHOLE_2.5_PLATED</field>
      </fields>
    </libpart>
    <libpart lib="working-eagle-import" part="RESISTOR_0603_NOOUT">
      <fields>
        <field name="Reference">R</field>
        <field name="Footprint">working:0603-NO</field>
      </fields>
      <pins>
        <pin num="1" name="1" type="passive"/>
        <pin num="2" name="2" type="passive"/>
      </pins>
    </libpart>
    <libpart lib="working-eagle-import" part="RESISTOR_4PACK">
      <fields>
        <field name="Reference">R</field>
        <field name="Footprint">working:RESPACK_4X0603</field>
      </fields>
      <pins>
        <pin num="1" name="1" type="passive"/>
        <pin num="2" name="1" type="passive"/>
        <pin num="3" name="1" type="passive"/>
        <pin num="4" name="1" type="passive"/>
        <pin num="5" name="2" type="passive"/>
        <pin num="6" name="2" type="passive"/>
        <pin num="7" name="2" type="passive"/>
        <pin num="8" name="2" type="passive"/>
      </pins>
    </libpart>
    <libpart lib="working-eagle-import" part="STEMMA_I2C_QT">
      <fields>
        <field name="Reference">CONN</field>
        <field name="Footprint">working:JST_SH4</field>
      </fields>
      <pins>
        <pin num="1" name="GND" type="passive"/>
        <pin num="2" name="V+" type="passive"/>
        <pin num="3" name="SDA" type="passive"/>
        <pin num="4" name="SCL" type="passive"/>
        <pin num="MT1" name="MT" type="bidirectional"/>
        <pin num="MT2" name="MT" type="bidirectional"/>
      </pins>
    </libpart>
    <libpart lib="working-eagle-import" part="VCNL4040M3OE">
      <fields>
        <field name="Reference">U</field>
        <field name="Footprint">working:VISHAY_VCNL4040_4X2X1.1</field>
      </fields>
      <pins>
        <pin num="1" name="GND" type="power_in"/>
        <pin num="2" name="C-SENSOR" type="output"/>
        <pin num="3" name="VDD" type="power_in"/>
        <pin num="4" name="VDD-LED" type="power_in"/>
        <pin num="5" name="C-LED" type="output"/>
        <pin num="6" name="INT" type="output"/>
        <pin num="7" name="SDA" type="bidirectional"/>
        <pin num="8" name="SCL" type="input"/>
      </pins>
    </libpart>
    <libpart lib="working-eagle-import" part="VREG_SOT23-5">
      <fields>
        <field name="Reference">U</field>
        <field name="Footprint">working:SOT23-5</field>
      </fields>
      <pins>
        <pin num="1" name="IN" type="power_in"/>
        <pin num="2" name="GND" type="power_in"/>
        <pin num="3" name="EN" type="input"/>
        <pin num="4" name="P4" type="bidirectional"/>
        <pin num="5" name="OUT" type="power_in"/>
      </pins>
    </libpart>
  </libparts>
  <libraries/>
  <nets>
    <net code="1" name="/INT">
      <node ref="JP1" pin="6" pinfunction="6" pintype="passive"/>
      <node ref="U3" pin="6" pinfunction="INT" pintype="output"/>
    </net>
    <net code="2" name="/SCL">
      <node ref="CONN3" pin="4" pinfunction="SCL" pintype="passive"/>
      <node ref="CONN4" pin="4" pinfunction="SCL" pintype="passive"/>
      <node ref="JP1" pin="4" pinfunction="4" pintype="passive"/>
      <node ref="Q2" pin="6" pinfunction="D" pintype="bidirectional"/>
      <node ref="R3" pin="8" pinfunction="2" pintype="passive"/>
    </net>
    <net code="3" name="/SCL_3V">
      <node ref="Q2" pin="1" pinfunction="S" pintype="bidirectional"/>
      <node ref="R3" pin="7" pinfunction="2" pintype="passive"/>
      <node ref="U3" pin="8" pinfunction="SCL" pintype="input"/>
    </net>
    <net code="4" name="/SDA">
      <node ref="CONN3" pin="3" pinfunction="SDA" pintype="passive"/>
      <node ref="CONN4" pin="3" pinfunction="SDA" pintype="passive"/>
      <node ref="JP1" pin="5" pinfunction="5" pintype="passive"/>
      <node ref="Q2" pin="3" pinfunction="D" pintype="bidirectional"/>
      <node ref="R3" pin="6" pinfunction="2" pintype="passive"/>
    </net>
    <net code="5" name="/SDA_3V">
      <node ref="Q2" pin="4" pinfunction="S" pintype="bidirectional"/>
      <node ref="R3" pin="5" pinfunction="2" pintype="passive"/>
      <node ref="U3" pin="7" pinfunction="SDA" pintype="bidirectional"/>
    </net>
    <net code="6" name="3.3V">
      <node ref="C1" pin="1" pinfunction="1" pintype="passive"/>
      <node ref="C3" pin="1" pinfunction="1" pintype="passive"/>
      <node ref="D1" pin="A" pinfunction="A" pintype="passive"/>
      <node ref="JP1" pin="2" pinfunction="2" pintype="passive"/>
      <node ref="Q2" pin="2" pinfunction="G" pintype="bidirectional"/>
      <node ref="Q2" pin="5" pinfunction="G" pintype="bidirectional"/>
      <node ref="R3" pin="2" pinfunction="1" pintype="passive"/>
      <node ref="R3" pin="4" pinfunction="1" pintype="passive"/>
      <node ref="U2" pin="5" pinfunction="OUT" pintype="power_in"/>
      <node ref="U3" pin="3" pinfunction="VDD" pintype="power_in"/>
      <node ref="U3" pin="4" pinfunction="VDD-LED" pintype="power_in"/>
    </net>
    <net code="7" name="GND">
      <node ref="C1" pin="2" pinfunction="2" pintype="passive"/>
      <node ref="C2" pin="2" pinfunction="2" pintype="passive"/>
      <node ref="C3" pin="2" pinfunction="2" pintype="passive"/>
      <node ref="CONN3" pin="1" pinfunction="GND" pintype="passive"/>
      <node ref="CONN4" pin="1" pinfunction="GND" pintype="passive"/>
      <node ref="JP1" pin="3" pinfunction="3" pintype="passive"/>
      <node ref="R1" pin="2" pinfunction="2" pintype="passive"/>
      <node ref="U2" pin="2" pinfunction="GND" pintype="power_in"/>
      <node ref="U3" pin="1" pinfunction="GND" pintype="power_in"/>
    </net>
    <net code="8" name="Net-(D1-PadC)">
      <node ref="D1" pin="C" pinfunction="C" pintype="passive"/>
      <node ref="R1" pin="1" pinfunction="1" pintype="passive"/>
    </net>
    <net code="9" name="Net-(U3-C-LED)">
      <node ref="U3" pin="2" pinfunction="C-SENSOR" pintype="output"/>
      <node ref="U3" pin="5" pinfunction="C-LED" pintype="output"/>
    </net>
    <net code="10" name="VCC">
      <node ref="C2" pin="1" pinfunction="1" pintype="passive"/>
      <node ref="CONN3" pin="2" pinfunction="V+" pintype="passive"/>
      <node ref="CONN4" pin="2" pinfunction="V+" pintype="passive"/>
      <node ref="JP1" pin="1" pinfunction="1" pintype="passive"/>
      <node ref="R3" pin="1" pinfunction="1" pintype="passive"/>
      <node ref="R3" pin="3" pinfunction="1" pintype="passive"/>
      <node ref="U2" pin="1" pinfunction="IN" pintype="power_in"/>
      <node ref="U2" pin="3" pinfunction="EN" pintype="input"/>
    </net>
    <net code="11" name="unconnected-(U2-P4-Pad4)">
      <node ref="U2" pin="4" pinfunction="P4" pintype="bidirectional"/>
    </net>
  </nets>
</export>
