<?xml version="1.0" encoding="UTF-8"?>
<export version="E">
  <design>
    <source>C:\gh\oomlout_oomp_project_bot_v_2\projects\adafruit_adafruit_crickit_pcbs_adafruit_crickit_for_microbit\current_version\working\working.kicad_sch</source>
    <date>13/09/2023 20:21:36</date>
    <tool>Eeschema 7.0.6</tool>
    <sheet number="1" name="/" tstamps="/">
      <title_block>
        <title/>
        <company/>
        <rev/>
        <date/>
        <source>working.kicad_sch</source>
        <comment number="1" value=""/>
        <comment number="2" value=""/>
        <comment number="3" value=""/>
        <comment number="4" value=""/>
        <comment number="5" value=""/>
        <comment number="6" value=""/>
        <comment number="7" value=""/>
        <comment number="8" value=""/>
        <comment number="9" value=""/>
      </title_block>
    </sheet>
    <sheet number="2" name="/working_1/" tstamps="/aa4cd7df-ef87-4e4a-88a7-69bd2f2ef4d8/">
      <title_block>
        <title/>
        <company/>
        <rev/>
        <date/>
        <source>working_1.kicad_sch</source>
        <comment number="1" value=""/>
        <comment number="2" value=""/>
        <comment number="3" value=""/>
        <comment number="4" value=""/>
        <comment number="5" value=""/>
        <comment number="6" value=""/>
        <comment number="7" value=""/>
        <comment number="8" value=""/>
        <comment number="9" value=""/>
      </title_block>
    </sheet>
    <sheet number="3" name="/working_2/" tstamps="/1b070554-f6ef-42d0-9c8c-81fbf4d5d42d/">
      <title_block>
        <title/>
        <company/>
        <rev/>
        <date/>
        <source>working_2.kicad_sch</source>
        <comment number="1" value=""/>
        <comment number="2" value=""/>
        <comment number="3" value=""/>
        <comment number="4" value=""/>
        <comment number="5" value=""/>
        <comment number="6" value=""/>
        <comment number="7" value=""/>
        <comment number="8" value=""/>
        <comment number="9" value=""/>
      </title_block>
    </sheet>
    <sheet number="4" name="/working_3/" tstamps="/e016b9fb-9b81-4597-8999-0de81b3cacc7/">
      <title_block>
        <title/>
        <company/>
        <rev/>
        <date/>
        <source>working_3.kicad_sch</source>
        <comment number="1" value=""/>
        <comment number="2" value=""/>
        <comment number="3" value=""/>
        <comment number="4" value=""/>
        <comment number="5" value=""/>
        <comment number="6" value=""/>
        <comment number="7" value=""/>
        <comment number="8" value=""/>
        <comment number="9" value=""/>
      </title_block>
    </sheet>
  </design>
  <components/>
  <libparts/>
  <libraries/>
  <nets/>
</export>
