<?xml version="1.0" encoding="UTF-8"?>
<export version="E">
  <design>
    <source>C:\gh\oomlout_oomp_project_bot_v_2\projects\adafruit_adafruit_flora_bluefruit_le_pcb_adafruit_flora_ble_friend\current_version\working\working.kicad_sch</source>
    <date>14/09/2023 02:30:57</date>
    <tool>Eeschema 7.0.6</tool>
    <sheet number="1" name="/" tstamps="/">
      <title_block>
        <title/>
        <company/>
        <rev/>
        <date/>
        <source>working.kicad_sch</source>
        <comment number="1" value=""/>
        <comment number="2" value=""/>
        <comment number="3" value=""/>
        <comment number="4" value=""/>
        <comment number="5" value=""/>
        <comment number="6" value=""/>
        <comment number="7" value=""/>
        <comment number="8" value=""/>
        <comment number="9" value=""/>
      </title_block>
    </sheet>
  </design>
  <components>
    <comp ref="C1">
      <value>1uF</value>
      <footprint>working:0805-NO</footprint>
      <libsource lib="working-eagle-import" part="CAP_CERAMIC0805-NOOUTLINE" description=""/>
      <property name="Sheetname" value=""/>
      <property name="Sheetfile" value="working.kicad_sch"/>
      <sheetpath names="/" tstamps="/"/>
      <tstamps>4bd34e64-a5ac-4f4d-85fa-4d562210e560</tstamps>
    </comp>
    <comp ref="C2">
      <value>1uF</value>
      <footprint>working:0805-NO</footprint>
      <libsource lib="working-eagle-import" part="CAP_CERAMIC0805-NOOUTLINE" description=""/>
      <property name="Sheetname" value=""/>
      <property name="Sheetfile" value="working.kicad_sch"/>
      <sheetpath names="/" tstamps="/"/>
      <tstamps>887d8400-921b-4712-81b3-17343ff315cb</tstamps>
    </comp>
    <comp ref="D1">
      <value>RED</value>
      <footprint>working:CHIPLED_0805_NOOUTLINE</footprint>
      <libsource lib="working-eagle-import" part="LED0805_NOOUTLINE" description=""/>
      <property name="Sheetname" value=""/>
      <property name="Sheetfile" value="working.kicad_sch"/>
      <sheetpath names="/" tstamps="/"/>
      <tstamps>855dccb4-b5a2-4045-a956-b096ff1d7ccf</tstamps>
    </comp>
    <comp ref="D2">
      <value>BLUE</value>
      <footprint>working:CHIPLED_0805_NOOUTLINE</footprint>
      <libsource lib="working-eagle-import" part="LED0805_NOOUTLINE" description=""/>
      <property name="Sheetname" value=""/>
      <property name="Sheetfile" value="working.kicad_sch"/>
      <sheetpath names="/" tstamps="/"/>
      <tstamps>a2aa7342-4e0a-49cb-80c1-0bcd1b1fc0e4</tstamps>
    </comp>
    <comp ref="DFU0">
      <value>KMR2</value>
      <footprint>working:BTN_KMR2_4.6X2.8</footprint>
      <libsource lib="working-eagle-import" part="SWITCH_TACT_SMT4.6X2.8" description=""/>
      <property name="Sheetname" value=""/>
      <property name="Sheetfile" value="working.kicad_sch"/>
      <sheetpath names="/" tstamps="/"/>
      <tstamps>361206d6-396f-4a1e-af68-be365f5a4ad5</tstamps>
    </comp>
    <comp ref="FID1">
      <value>FIDUCIAL""</value>
      <footprint>working:FIDUCIAL_1MM</footprint>
      <libsource lib="working-eagle-import" part="FIDUCIAL{dblquote}{dblquote}" description=""/>
      <property name="Sheetname" value=""/>
      <property name="Sheetfile" value="working.kicad_sch"/>
      <sheetpath names="/" tstamps="/"/>
      <tstamps>c17f5d5d-8288-4e1c-9723-976bb7f624f8</tstamps>
    </comp>
    <comp ref="FID2">
      <value>FIDUCIAL""</value>
      <footprint>working:FIDUCIAL_1MM</footprint>
      <libsource lib="working-eagle-import" part="FIDUCIAL{dblquote}{dblquote}" description=""/>
      <property name="Sheetname" value=""/>
      <property name="Sheetfile" value="working.kicad_sch"/>
      <sheetpath names="/" tstamps="/"/>
      <tstamps>1adcb48b-3724-4dc3-afc2-e525893b7480</tstamps>
    </comp>
    <comp ref="GND0">
      <value>SEWTAP-2.0IN</value>
      <footprint>working:SEWINGTAP_2.0</footprint>
      <libsource lib="working-eagle-import" part="SEWTAP-2.0IN" description=""/>
      <property name="Sheetname" value=""/>
      <property name="Sheetfile" value="working.kicad_sch"/>
      <sheetpath names="/" tstamps="/"/>
      <tstamps>c2b70577-0f0d-44f1-b980-ef8a34dcc5b5</tstamps>
    </comp>
    <comp ref="R1">
      <value>2K</value>
      <footprint>working:0805-NO</footprint>
      <libsource lib="working-eagle-import" part="RESISTOR0805_NOOUTLINE" description=""/>
      <property name="Sheetname" value=""/>
      <property name="Sheetfile" value="working.kicad_sch"/>
      <sheetpath names="/" tstamps="/"/>
      <tstamps>35db50d3-d635-49fb-aa73-948ab2f93ec2</tstamps>
    </comp>
    <comp ref="R2">
      <value>2K</value>
      <footprint>working:0805-NO</footprint>
      <libsource lib="working-eagle-import" part="RESISTOR0805_NOOUTLINE" description=""/>
      <property name="Sheetname" value=""/>
      <property name="Sheetfile" value="working.kicad_sch"/>
      <sheetpath names="/" tstamps="/"/>
      <tstamps>83565a65-db5e-4c41-a120-863c04cb6879</tstamps>
    </comp>
    <comp ref="R3">
      <value>10K</value>
      <footprint>working:0805-NO</footprint>
      <libsource lib="working-eagle-import" part="RESISTOR0805_NOOUTLINE" description=""/>
      <property name="Sheetname" value=""/>
      <property name="Sheetfile" value="working.kicad_sch"/>
      <sheetpath names="/" tstamps="/"/>
      <tstamps>0ed4061b-c974-495c-b5cd-5b4733bf6887</tstamps>
    </comp>
    <comp ref="R4">
      <value>2K</value>
      <footprint>working:0805-NO</footprint>
      <libsource lib="working-eagle-import" part="RESISTOR0805_NOOUTLINE" description=""/>
      <property name="Sheetname" value=""/>
      <property name="Sheetfile" value="working.kicad_sch"/>
      <sheetpath names="/" tstamps="/"/>
      <tstamps>43141ce8-82bc-4f1b-9d05-f05c4aa31f1b</tstamps>
    </comp>
    <comp ref="RX0">
      <value>SEWTAP-2.0IN</value>
      <footprint>working:SEWINGTAP_2.0</footprint>
      <libsource lib="working-eagle-import" part="SEWTAP-2.0IN" description=""/>
      <property name="Sheetname" value=""/>
      <property name="Sheetfile" value="working.kicad_sch"/>
      <sheetpath names="/" tstamps="/"/>
      <tstamps>e7b3335b-34a0-4e8d-8bd3-54bc080c4a3a</tstamps>
    </comp>
    <comp ref="SW1">
      <value>EG1319</value>
      <footprint>working:EG1390</footprint>
      <libsource lib="working-eagle-import" part="SWITCH_DPDTEG1390" description=""/>
      <property name="Sheetname" value=""/>
      <property name="Sheetfile" value="working.kicad_sch"/>
      <sheetpath names="/" tstamps="/"/>
      <tstamps>bd9e7330-d607-469d-9fe1-597775c93b78</tstamps>
    </comp>
    <comp ref="TP1">
      <value>SEWTAP-2.0IN</value>
      <footprint>working:SEWINGTAP_2.0</footprint>
      <libsource lib="working-eagle-import" part="SEWTAP-2.0IN" description=""/>
      <property name="Sheetname" value=""/>
      <property name="Sheetfile" value="working.kicad_sch"/>
      <sheetpath names="/" tstamps="/"/>
      <tstamps>b064e1bb-8e78-4d7f-a17b-fc170360d548</tstamps>
    </comp>
    <comp ref="TP2">
      <value>SWCLK</value>
      <footprint>working:PAD-1.5X2.0</footprint>
      <libsource lib="working-eagle-import" part="TESTPOINT1.5X2.0MM_NOCREAM" description=""/>
      <property name="Sheetname" value=""/>
      <property name="Sheetfile" value="working.kicad_sch"/>
      <sheetpath names="/" tstamps="/"/>
      <tstamps>9519e469-1aaa-4503-8b22-193bd3991743</tstamps>
    </comp>
    <comp ref="TP3">
      <value>SWDIO</value>
      <footprint>working:PAD-1.5X2.0</footprint>
      <libsource lib="working-eagle-import" part="TESTPOINT1.5X2.0MM_NOCREAM" description=""/>
      <property name="Sheetname" value=""/>
      <property name="Sheetfile" value="working.kicad_sch"/>
      <sheetpath names="/" tstamps="/"/>
      <tstamps>5b152f25-fe64-4d86-83db-a8665bf317c5</tstamps>
    </comp>
    <comp ref="TP5">
      <value>FCTRST</value>
      <footprint>working:PAD-1.5X2.0</footprint>
      <libsource lib="working-eagle-import" part="TESTPOINT1.5X2.0MM_NOCREAM" description=""/>
      <property name="Sheetname" value=""/>
      <property name="Sheetfile" value="working.kicad_sch"/>
      <sheetpath names="/" tstamps="/"/>
      <tstamps>8f66ee15-1957-46da-8da9-0701427a8f04</tstamps>
    </comp>
    <comp ref="TX0">
      <value>SEWTAP-2.0IN</value>
      <footprint>working:SEWINGTAP_2.0</footprint>
      <libsource lib="working-eagle-import" part="SEWTAP-2.0IN" description=""/>
      <property name="Sheetname" value=""/>
      <property name="Sheetfile" value="working.kicad_sch"/>
      <sheetpath names="/" tstamps="/"/>
      <tstamps>00250a2a-008c-4b4d-94d9-03005bcbefef</tstamps>
    </comp>
    <comp ref="U1">
      <value>MBT40</value>
      <footprint>working:BLE_MODULE_RAYTAC_MDBT40</footprint>
      <libsource lib="working-eagle-import" part="NRF51822_MODULE_MDBT40" description=""/>
      <property name="Sheetname" value=""/>
      <property name="Sheetfile" value="working.kicad_sch"/>
      <sheetpath names="/" tstamps="/"/>
      <tstamps>993617a7-64e7-4f66-a543-501556cab135</tstamps>
    </comp>
    <comp ref="UNK3V3IN0">
      <value>SEWTAP-2.0IN</value>
      <footprint>working:SEWINGTAP_2.0</footprint>
      <libsource lib="working-eagle-import" part="SEWTAP-2.0IN" description=""/>
      <property name="Sheetname" value=""/>
      <property name="Sheetfile" value="working.kicad_sch"/>
      <sheetpath names="/" tstamps="/"/>
      <tstamps>b500722a-5379-4866-b114-294c29a90d3d</tstamps>
    </comp>
    <comp ref="Y1">
      <value>32.768kHz (535-9166-2-ND)</value>
      <footprint>working:CRYSTAL_CYL_2X6MM_SMT</footprint>
      <libsource lib="working-eagle-import" part="CRYSTAL2.0X6.0_32.768" description=""/>
      <property name="Sheetname" value=""/>
      <property name="Sheetfile" value="working.kicad_sch"/>
      <sheetpath names="/" tstamps="/"/>
      <tstamps>df97b502-d509-4060-bb88-2ac8f5217616</tstamps>
    </comp>
  </components>
  <libparts>
    <libpart lib="working-eagle-import" part="CAP_CERAMIC0805-NOOUTLINE">
      <fields>
        <field name="Reference">C</field>
        <field name="Footprint">working:0805-NO</field>
      </fields>
      <pins>
        <pin num="1" name="1" type="passive"/>
        <pin num="2" name="2" type="passive"/>
      </pins>
    </libpart>
    <libpart lib="working-eagle-import" part="CRYSTAL2.0X6.0_32.768">
      <fields>
        <field name="Reference">Y</field>
        <field name="Footprint">working:CRYSTAL_CYL_2X6MM_SMT</field>
      </fields>
      <pins>
        <pin num="1" name="1" type="passive"/>
        <pin num="2" name="2" type="passive"/>
      </pins>
    </libpart>
    <libpart lib="working-eagle-import" part="FIDUCIAL{dblquote}{dblquote}">
      <fields>
        <field name="Reference">FID</field>
        <field name="Footprint">working:FIDUCIAL_1MM</field>
      </fields>
    </libpart>
    <libpart lib="working-eagle-import" part="LED0805_NOOUTLINE">
      <fields>
        <field name="Reference">D</field>
        <field name="Footprint">working:CHIPLED_0805_NOOUTLINE</field>
      </fields>
      <pins>
        <pin num="A" name="A" type="passive"/>
        <pin num="C" name="C" type="passive"/>
      </pins>
    </libpart>
    <libpart lib="working-eagle-import" part="NRF51822_MODULE_MDBT40">
      <fields>
        <field name="Reference">U</field>
        <field name="Footprint">working:BLE_MODULE_RAYTAC_MDBT40</field>
      </fields>
      <pins>
        <pin num="1" name="GND@1" type="power_in"/>
        <pin num="2" name="GND@2" type="power_in"/>
        <pin num="3" name="AVDD" type="power_in"/>
        <pin num="4" name="P0.21" type="bidirectional"/>
        <pin num="5" name="P0.22" type="bidirectional"/>
        <pin num="6" name="P0.23" type="bidirectional"/>
        <pin num="7" name="P0.24" type="bidirectional"/>
        <pin num="8" name="P0.25" type="bidirectional"/>
        <pin num="9" name="P0.26/AIN0/XL2" type="bidirectional"/>
        <pin num="10" name="P0.27/AIN1/XL1" type="bidirectional"/>
        <pin num="11" name="P0.28" type="bidirectional"/>
        <pin num="12" name="P0.29" type="bidirectional"/>
        <pin num="13" name="GND@3" type="power_in"/>
        <pin num="14" name="VDD" type="power_in"/>
        <pin num="15" name="DCC" type="power_in"/>
        <pin num="16" name="P0.30" type="bidirectional"/>
        <pin num="17" name="P0.00/AREF0" type="bidirectional"/>
        <pin num="18" name="P0.01/AIN2" type="bidirectional"/>
        <pin num="19" name="P0.02/AIN3" type="bidirectional"/>
        <pin num="20" name="P0.03/AIN4" type="bidirectional"/>
        <pin num="21" name="P0.04/AIN5" type="bidirectional"/>
        <pin num="22" name="P0.05/AIN6" type="bidirectional"/>
        <pin num="23" name="P0.06/AIN7/AREF1" type="bidirectional"/>
        <pin num="24" name="P0.07" type="bidirectional"/>
        <pin num="25" name="GND@4" type="power_in"/>
        <pin num="26" name="P0.08" type="bidirectional"/>
        <pin num="27" name="P0.09" type="bidirectional"/>
        <pin num="28" name="P0.10" type="bidirectional"/>
        <pin num="29" name="P0.11" type="bidirectional"/>
        <pin num="30" name="P0.12" type="bidirectional"/>
        <pin num="31" name="P0.13" type="bidirectional"/>
        <pin num="32" name="P0.14" type="bidirectional"/>
        <pin num="33" name="P0.15" type="bidirectional"/>
        <pin num="34" name="P0.16" type="bidirectional"/>
        <pin num="35" name="SWDIO/NRESET" type="bidirectional"/>
        <pin num="36" name="SWCLK" type="bidirectional"/>
        <pin num="37" name="P0.17" type="bidirectional"/>
        <pin num="38" name="P0.18" type="bidirectional"/>
        <pin num="39" name="P0.19" type="bidirectional"/>
        <pin num="40" name="P0.20" type="bidirectional"/>
        <pin num="41" name="DEC2" type="power_in"/>
        <pin num="42" name="GND@5" type="power_in"/>
      </pins>
    </libpart>
    <libpart lib="working-eagle-import" part="RESISTOR0805_NOOUTLINE">
      <fields>
        <field name="Reference">R</field>
        <field name="Footprint">working:0805-NO</field>
      </fields>
      <pins>
        <pin num="1" name="1" type="passive"/>
        <pin num="2" name="2" type="passive"/>
      </pins>
    </libpart>
    <libpart lib="working-eagle-import" part="SEWTAP-2.0IN">
      <fields>
        <field name="Reference">TP</field>
        <field name="Footprint">working:SEWINGTAP_2.0</field>
      </fields>
      <pins>
        <pin num="P$1" name="SEW" type="bidirectional"/>
      </pins>
    </libpart>
    <libpart lib="working-eagle-import" part="SWITCH_DPDTEG1390">
      <fields>
        <field name="Reference">SW</field>
        <field name="Footprint">working:EG1390</field>
      </fields>
      <pins>
        <pin num="O1" name="O1" type="passive"/>
        <pin num="O2" name="O2" type="passive"/>
        <pin num="P1" name="P1" type="passive"/>
        <pin num="P2" name="P2" type="passive"/>
        <pin num="S1" name="S1" type="passive"/>
        <pin num="S2" name="S2" type="passive"/>
      </pins>
    </libpart>
    <libpart lib="working-eagle-import" part="SWITCH_TACT_SMT4.6X2.8">
      <fields>
        <field name="Reference">SW</field>
        <field name="Footprint">working:BTN_KMR2_4.6X2.8</field>
      </fields>
      <pins>
        <pin num="A" name="P" type="passive"/>
        <pin num="A'" name="P1" type="passive"/>
        <pin num="B" name="S" type="passive"/>
        <pin num="B'" name="S1" type="passive"/>
      </pins>
    </libpart>
    <libpart lib="working-eagle-import" part="TESTPOINT1.5X2.0MM_NOCREAM">
      <fields>
        <field name="Reference">TP</field>
        <field name="Footprint">working:PAD-1.5X2.0</field>
      </fields>
      <pins>
        <pin num="P$1" name="P$1" type="bidirectional"/>
      </pins>
    </libpart>
  </libparts>
  <libraries/>
  <nets>
    <net code="1" name="/CONN_LED">
      <node ref="R2" pin="1" pinfunction="1" pintype="passive"/>
      <node ref="U1" pin="39" pinfunction="P0.19" pintype="bidirectional"/>
    </net>
    <net code="2" name="/DFU">
      <node ref="DFU0" pin="A" pinfunction="P" pintype="passive"/>
      <node ref="DFU0" pin="A'" pinfunction="P1" pintype="passive"/>
      <node ref="R3" pin="2" pinfunction="2" pintype="passive"/>
      <node ref="U1" pin="24" pinfunction="P0.07" pintype="bidirectional"/>
    </net>
    <net code="3" name="/FCTRYRST_3V">
      <node ref="TP5" pin="P$1" pinfunction="P$1" pintype="bidirectional"/>
      <node ref="U1" pin="34" pinfunction="P0.16" pintype="bidirectional"/>
    </net>
    <net code="4" name="/MODE">
      <node ref="R4" pin="1" pinfunction="1" pintype="passive"/>
      <node ref="TP1" pin="P$1" pinfunction="SEW" pintype="bidirectional"/>
      <node ref="U1" pin="18" pinfunction="P0.01/AIN2" pintype="bidirectional"/>
    </net>
    <net code="5" name="/MODE_LED">
      <node ref="R1" pin="1" pinfunction="1" pintype="passive"/>
      <node ref="U1" pin="38" pinfunction="P0.18" pintype="bidirectional"/>
    </net>
    <net code="6" name="/RXI">
      <node ref="RX0" pin="P$1" pinfunction="SEW" pintype="bidirectional"/>
      <node ref="U1" pin="29" pinfunction="P0.11" pintype="bidirectional"/>
    </net>
    <net code="7" name="/SWCLK">
      <node ref="TP2" pin="P$1" pinfunction="P$1" pintype="bidirectional"/>
      <node ref="U1" pin="36" pinfunction="SWCLK" pintype="bidirectional"/>
    </net>
    <net code="8" name="/SWDIO{slash}RST_3V">
      <node ref="TP3" pin="P$1" pinfunction="P$1" pintype="bidirectional"/>
      <node ref="U1" pin="35" pinfunction="SWDIO/NRESET" pintype="bidirectional"/>
    </net>
    <net code="9" name="/TXO">
      <node ref="TX0" pin="P$1" pinfunction="SEW" pintype="bidirectional"/>
      <node ref="U1" pin="27" pinfunction="P0.09" pintype="bidirectional"/>
    </net>
    <net code="10" name="3.3V">
      <node ref="C1" pin="1" pinfunction="1" pintype="passive"/>
      <node ref="C2" pin="1" pinfunction="1" pintype="passive"/>
      <node ref="R3" pin="1" pinfunction="1" pintype="passive"/>
      <node ref="SW1" pin="O1" pinfunction="O1" pintype="passive"/>
      <node ref="SW1" pin="O2" pinfunction="O2" pintype="passive"/>
      <node ref="U1" pin="14" pinfunction="VDD" pintype="power_in"/>
      <node ref="U1" pin="3" pinfunction="AVDD" pintype="power_in"/>
      <node ref="UNK3V3IN0" pin="P$1" pinfunction="SEW" pintype="bidirectional"/>
    </net>
    <net code="11" name="DCC">
      <node ref="U1" pin="15" pinfunction="DCC" pintype="power_in"/>
    </net>
    <net code="12" name="DEC2">
      <node ref="U1" pin="41" pinfunction="DEC2" pintype="power_in"/>
    </net>
    <net code="13" name="GND">
      <node ref="C1" pin="2" pinfunction="2" pintype="passive"/>
      <node ref="C2" pin="2" pinfunction="2" pintype="passive"/>
      <node ref="D1" pin="C" pinfunction="C" pintype="passive"/>
      <node ref="D2" pin="C" pinfunction="C" pintype="passive"/>
      <node ref="DFU0" pin="B" pinfunction="S" pintype="passive"/>
      <node ref="DFU0" pin="B'" pinfunction="S1" pintype="passive"/>
      <node ref="GND0" pin="P$1" pinfunction="SEW" pintype="bidirectional"/>
      <node ref="SW1" pin="S1" pinfunction="S1" pintype="passive"/>
      <node ref="SW1" pin="S2" pinfunction="S2" pintype="passive"/>
      <node ref="U1" pin="1" pinfunction="GND@1" pintype="power_in"/>
      <node ref="U1" pin="13" pinfunction="GND@3" pintype="power_in"/>
      <node ref="U1" pin="16" pinfunction="P0.30" pintype="bidirectional"/>
      <node ref="U1" pin="2" pinfunction="GND@2" pintype="power_in"/>
      <node ref="U1" pin="25" pinfunction="GND@4" pintype="power_in"/>
      <node ref="U1" pin="28" pinfunction="P0.10" pintype="bidirectional"/>
      <node ref="U1" pin="42" pinfunction="GND@5" pintype="power_in"/>
    </net>
    <net code="14" name="Net-(D1-PadA)">
      <node ref="D1" pin="A" pinfunction="A" pintype="passive"/>
      <node ref="R1" pin="2" pinfunction="2" pintype="passive"/>
    </net>
    <net code="15" name="Net-(D2-PadA)">
      <node ref="D2" pin="A" pinfunction="A" pintype="passive"/>
      <node ref="R2" pin="2" pinfunction="2" pintype="passive"/>
    </net>
    <net code="16" name="Net-(R4-Pad2)">
      <node ref="R4" pin="2" pinfunction="2" pintype="passive"/>
      <node ref="SW1" pin="P1" pinfunction="P1" pintype="passive"/>
      <node ref="SW1" pin="P2" pinfunction="P2" pintype="passive"/>
    </net>
    <net code="17" name="Net-(U1-P0.26{slash}AIN0{slash}XL2)">
      <node ref="U1" pin="9" pinfunction="P0.26/AIN0/XL2" pintype="bidirectional"/>
      <node ref="Y1" pin="1" pinfunction="1" pintype="passive"/>
    </net>
    <net code="18" name="Net-(U1-P0.27{slash}AIN1{slash}XL1)">
      <node ref="U1" pin="10" pinfunction="P0.27/AIN1/XL1" pintype="bidirectional"/>
      <node ref="Y1" pin="2" pinfunction="2" pintype="passive"/>
    </net>
    <net code="19" name="unconnected-(U1-P0.00{slash}AREF0-Pad17)">
      <node ref="U1" pin="17" pinfunction="P0.00/AREF0" pintype="bidirectional"/>
    </net>
    <net code="20" name="unconnected-(U1-P0.02{slash}AIN3-Pad19)">
      <node ref="U1" pin="19" pinfunction="P0.02/AIN3" pintype="bidirectional"/>
    </net>
    <net code="21" name="unconnected-(U1-P0.03{slash}AIN4-Pad20)">
      <node ref="U1" pin="20" pinfunction="P0.03/AIN4" pintype="bidirectional"/>
    </net>
    <net code="22" name="unconnected-(U1-P0.04{slash}AIN5-Pad21)">
      <node ref="U1" pin="21" pinfunction="P0.04/AIN5" pintype="bidirectional"/>
    </net>
    <net code="23" name="unconnected-(U1-P0.05{slash}AIN6-Pad22)">
      <node ref="U1" pin="22" pinfunction="P0.05/AIN6" pintype="bidirectional"/>
    </net>
    <net code="24" name="unconnected-(U1-P0.06{slash}AIN7{slash}AREF1-Pad23)">
      <node ref="U1" pin="23" pinfunction="P0.06/AIN7/AREF1" pintype="bidirectional"/>
    </net>
    <net code="25" name="unconnected-(U1-P0.08-Pad26)">
      <node ref="U1" pin="26" pinfunction="P0.08" pintype="bidirectional"/>
    </net>
    <net code="26" name="unconnected-(U1-P0.12-Pad30)">
      <node ref="U1" pin="30" pinfunction="P0.12" pintype="bidirectional"/>
    </net>
    <net code="27" name="unconnected-(U1-P0.13-Pad31)">
      <node ref="U1" pin="31" pinfunction="P0.13" pintype="bidirectional"/>
    </net>
    <net code="28" name="unconnected-(U1-P0.14-Pad32)">
      <node ref="U1" pin="32" pinfunction="P0.14" pintype="bidirectional"/>
    </net>
    <net code="29" name="unconnected-(U1-P0.15-Pad33)">
      <node ref="U1" pin="33" pinfunction="P0.15" pintype="bidirectional"/>
    </net>
    <net code="30" name="unconnected-(U1-P0.17-Pad37)">
      <node ref="U1" pin="37" pinfunction="P0.17" pintype="bidirectional"/>
    </net>
    <net code="31" name="unconnected-(U1-P0.20-Pad40)">
      <node ref="U1" pin="40" pinfunction="P0.20" pintype="bidirectional"/>
    </net>
    <net code="32" name="unconnected-(U1-P0.21-Pad4)">
      <node ref="U1" pin="4" pinfunction="P0.21" pintype="bidirectional"/>
    </net>
    <net code="33" name="unconnected-(U1-P0.22-Pad5)">
      <node ref="U1" pin="5" pinfunction="P0.22" pintype="bidirectional"/>
    </net>
    <net code="34" name="unconnected-(U1-P0.23-Pad6)">
      <node ref="U1" pin="6" pinfunction="P0.23" pintype="bidirectional"/>
    </net>
    <net code="35" name="unconnected-(U1-P0.24-Pad7)">
      <node ref="U1" pin="7" pinfunction="P0.24" pintype="bidirectional"/>
    </net>
    <net code="36" name="unconnected-(U1-P0.25-Pad8)">
      <node ref="U1" pin="8" pinfunction="P0.25" pintype="bidirectional"/>
    </net>
    <net code="37" name="unconnected-(U1-P0.28-Pad11)">
      <node ref="U1" pin="11" pinfunction="P0.28" pintype="bidirectional"/>
    </net>
    <net code="38" name="unconnected-(U1-P0.29-Pad12)">
      <node ref="U1" pin="12" pinfunction="P0.29" pintype="bidirectional"/>
    </net>
  </nets>
</export>
